{
  "reviews": [
    {
      "id": "R-001",
      "name": "مي الخثعمي",
      "stars": 5,
      "tag": "الخطة",
      "text": "التحليل واضح، وعرفني أضعف قسمين عندي بدون لف ودوران.",
      "time_label": "2026"
    },
    {
      "id": "R-002",
      "name": "لمى السلمي",
      "stars": 5,
      "tag": "التركيز",
      "text": "الكويزات بعد ما أخلصها ترجعني لأخطائي وهذا اللي كنت أحتاجه.",
      "time_label": "2026"
    },
    {
      "id": "R-003",
      "name": "عبدالعزيز العبدلي",
      "stars": 5,
      "tag": "منع التشتيت",
      "text": "أعجبني خيار إيقاف الشرح عشان أختبر نفسي بجد.",
      "time_label": "2026"
    },
    {
      "id": "R-004",
      "name": "أنس العبيدي",
      "stars": 5,
      "tag": "منع التشتيت",
      "text": "النتيجة مو بس رقم… عطاني خطة تناسب موعد اختباري.",
      "time_label": "2026"
    },
    {
      "id": "R-005",
      "name": "زياد العيد",
      "stars": 5,
      "tag": "الـPDF",
      "text": "أعجبني خيار إيقاف الشرح عشان أختبر نفسي بجد.",
      "time_label": "2026"
    },
    {
      "id": "R-006",
      "name": "شذى العمري",
      "stars": 5,
      "tag": "الخطة",
      "text": "النتيجة مو بس رقم… عطاني خطة تناسب موعد اختباري.",
      "time_label": "2026"
    },
    {
      "id": "R-007",
      "name": "نوف الحربي",
      "stars": 5,
      "tag": "الـPDF",
      "text": "حلو إن فيه محاولة واحدة كل 24 ساعة… تجبرك تذاكر بدل تكرر اختبار.",
      "time_label": "2026"
    },
    {
      "id": "R-008",
      "name": "حازم الرويلي",
      "stars": 5,
      "tag": "الـPDF",
      "text": "أعجبني خيار إيقاف الشرح عشان أختبر نفسي بجد.",
      "time_label": "2026"
    },
    {
      "id": "R-009",
      "name": "ماجد العبيدي",
      "stars": 5,
      "tag": "الكويزات",
      "text": "البرنامج ساعدني أرتب وقتي حتى لو عندي 30 دقيقة بس.",
      "time_label": "2026"
    },
    {
      "id": "R-010",
      "name": "سهيل الماجدي",
      "stars": 5,
      "tag": "سهولة الاستخدام",
      "text": "الجدول اليومي خلاني ألتزم… أول مرة أحس إن عندي مسار.",
      "time_label": "2026"
    },
    {
      "id": "R-011",
      "name": "علي العمري",
      "stars": 5,
      "tag": "الـPDF",
      "text": "النتيجة مو بس رقم… عطاني خطة تناسب موعد اختباري.",
      "time_label": "2026"
    },
    {
      "id": "R-012",
      "name": "باسل الزبيدي",
      "stars": 5,
      "tag": "المساعد",
      "text": "أعجبني خيار إيقاف الشرح عشان أختبر نفسي بجد.",
      "time_label": "2026"
    },
    {
      "id": "R-013",
      "name": "سلمان العتيبي",
      "stars": 5,
      "tag": "الجدول",
      "text": "الجدول اليومي خلاني ألتزم… أول مرة أحس إن عندي مسار.",
      "time_label": "2026"
    },
    {
      "id": "R-014",
      "name": "مهند التميمي",
      "stars": 5,
      "tag": "الـPDF",
      "text": "ميزة تحميل الـPDF ممتازة — أحطه قدامي وأشيك الإنجاز.",
      "time_label": "2026"
    },
    {
      "id": "R-015",
      "name": "ورود البلوي",
      "stars": 5,
      "tag": "الكويزات",
      "text": "ميزة تحميل الـPDF ممتازة — أحطه قدامي وأشيك الإنجاز.",
      "time_label": "2026"
    },
    {
      "id": "R-016",
      "name": "نادر المرزوقي",
      "stars": 5,
      "tag": "الجدول",
      "text": "واجهة هادية ومريحة وما فيها زحمة.",
      "time_label": "2026"
    },
    {
      "id": "R-017",
      "name": "عائشة الحربي",
      "stars": 5,
      "tag": "الـPDF",
      "text": "حلو إن فيه محاولة واحدة كل 24 ساعة… تجبرك تذاكر بدل تكرر اختبار.",
      "time_label": "2026"
    },
    {
      "id": "R-018",
      "name": "ثامر الحجيلي",
      "stars": 5,
      "tag": "الـPDF",
      "text": "أعجبني خيار إيقاف الشرح عشان أختبر نفسي بجد.",
      "time_label": "2026"
    },
    {
      "id": "R-019",
      "name": "ريان القصيمي",
      "stars": 5,
      "tag": "الجدول",
      "text": "الجدول اليومي خلاني ألتزم… أول مرة أحس إن عندي مسار.",
      "time_label": "2026"
    },
    {
      "id": "R-020",
      "name": "معاذ العنزي",
      "stars": 5,
      "tag": "التركيز",
      "text": "النتيجة مو بس رقم… عطاني خطة تناسب موعد اختباري.",
      "time_label": "2026"
    },
    {
      "id": "R-021",
      "name": "أبرار الفيفي",
      "stars": 5,
      "tag": "الـPDF",
      "text": "حلو إن فيه محاولة واحدة كل 24 ساعة… تجبرك تذاكر بدل تكرر اختبار.",
      "time_label": "2026"
    },
    {
      "id": "R-022",
      "name": "يزيد العنزي",
      "stars": 5,
      "tag": "سهولة الاستخدام",
      "text": "أعجبني خيار إيقاف الشرح عشان أختبر نفسي بجد.",
      "time_label": "2026"
    },
    {
      "id": "R-023",
      "name": "غيداء السهلي",
      "stars": 5,
      "tag": "منع التشتيت",
      "text": "البرنامج ساعدني أرتب وقتي حتى لو عندي 30 دقيقة بس.",
      "time_label": "2026"
    },
    {
      "id": "R-024",
      "name": "إبراهيم العنزي",
      "stars": 5,
      "tag": "سهولة الاستخدام",
      "text": "واجهة هادية ومريحة وما فيها زحمة.",
      "time_label": "2026"
    },
    {
      "id": "R-025",
      "name": "مي الهاجري",
      "stars": 5,
      "tag": "المساعد",
      "text": "حلو إن فيه محاولة واحدة كل 24 ساعة… تجبرك تذاكر بدل تكرر اختبار.",
      "time_label": "2026"
    },
    {
      "id": "R-026",
      "name": "ريان الحسن",
      "stars": 5,
      "tag": "الكويزات",
      "text": "ميزة تحميل الـPDF ممتازة — أحطه قدامي وأشيك الإنجاز.",
      "time_label": "2026"
    },
    {
      "id": "R-027",
      "name": "راشد العبدلي",
      "stars": 5,
      "tag": "منع التشتيت",
      "text": "حلو إن فيه محاولة واحدة كل 24 ساعة… تجبرك تذاكر بدل تكرر اختبار.",
      "time_label": "2026"
    },
    {
      "id": "R-028",
      "name": "مراد الهاجري",
      "stars": 5,
      "tag": "سهولة الاستخدام",
      "text": "واجهة هادية ومريحة وما فيها زحمة.",
      "time_label": "2026"
    },
    {
      "id": "R-029",
      "name": "دانه الحريري",
      "stars": 5,
      "tag": "الجدول",
      "text": "الجدول اليومي خلاني ألتزم… أول مرة أحس إن عندي مسار.",
      "time_label": "2026"
    },
    {
      "id": "R-030",
      "name": "مزن الزيدي",
      "stars": 5,
      "tag": "الجدول",
      "text": "النتيجة مو بس رقم… عطاني خطة تناسب موعد اختباري.",
      "time_label": "2026"
    },
    {
      "id": "R-031",
      "name": "غيداء العقيل",
      "stars": 5,
      "tag": "منع التشتيت",
      "text": "الجدول اليومي خلاني ألتزم… أول مرة أحس إن عندي مسار.",
      "time_label": "2026"
    },
    {
      "id": "R-032",
      "name": "سارة المحيميد",
      "stars": 5,
      "tag": "الكويزات",
      "text": "أعجبني خيار إيقاف الشرح عشان أختبر نفسي بجد.",
      "time_label": "2026"
    },
    {
      "id": "R-033",
      "name": "لميس السيف",
      "stars": 5,
      "tag": "التركيز",
      "text": "الكويزات بعد ما أخلصها ترجعني لأخطائي وهذا اللي كنت أحتاجه.",
      "time_label": "2026"
    },
    {
      "id": "R-034",
      "name": "عائشة العيسى",
      "stars": 5,
      "tag": "الخطة",
      "text": "حلو إن فيه محاولة واحدة كل 24 ساعة… تجبرك تذاكر بدل تكرر اختبار.",
      "time_label": "2026"
    },
    {
      "id": "R-035",
      "name": "ماجد الماجدي",
      "stars": 5,
      "tag": "الـPDF",
      "text": "التحليل واضح، وعرفني أضعف قسمين عندي بدون لف ودوران.",
      "time_label": "2026"
    },
    {
      "id": "R-036",
      "name": "زينب السديري",
      "stars": 5,
      "tag": "الكويزات",
      "text": "النتيجة مو بس رقم… عطاني خطة تناسب موعد اختباري.",
      "time_label": "2026"
    },
    {
      "id": "R-037",
      "name": "أسماء الرشيدي",
      "stars": 5,
      "tag": "الجدول",
      "text": "أفضل شيء: ما تتشتت بين مصادر كثيرة.",
      "time_label": "2026"
    },
    {
      "id": "R-038",
      "name": "معتز العوفي",
      "stars": 5,
      "tag": "الكويزات",
      "text": "البرنامج ساعدني أرتب وقتي حتى لو عندي 30 دقيقة بس.",
      "time_label": "2026"
    },
    {
      "id": "R-039",
      "name": "بدر المنصوري",
      "stars": 5,
      "tag": "المساعد",
      "text": "النتيجة مو بس رقم… عطاني خطة تناسب موعد اختباري.",
      "time_label": "2026"
    },
    {
      "id": "R-040",
      "name": "مشعل المنصوري",
      "stars": 5,
      "tag": "سهولة الاستخدام",
      "text": "الجدول اليومي خلاني ألتزم… أول مرة أحس إن عندي مسار.",
      "time_label": "2026"
    },
    {
      "id": "R-041",
      "name": "فارس الحسن",
      "stars": 5,
      "tag": "سهولة الاستخدام",
      "text": "البرنامج ساعدني أرتب وقتي حتى لو عندي 30 دقيقة بس.",
      "time_label": "2026"
    },
    {
      "id": "R-042",
      "name": "علي السديري",
      "stars": 5,
      "tag": "الجدول",
      "text": "واجهة هادية ومريحة وما فيها زحمة.",
      "time_label": "2026"
    },
    {
      "id": "R-043",
      "name": "نادر العيد",
      "stars": 5,
      "tag": "المساعد",
      "text": "ميزة تحميل الـPDF ممتازة — أحطه قدامي وأشيك الإنجاز.",
      "time_label": "2026"
    },
    {
      "id": "R-044",
      "name": "آلاء الحمادي",
      "stars": 5,
      "tag": "الـPDF",
      "text": "التحليل واضح، وعرفني أضعف قسمين عندي بدون لف ودوران.",
      "time_label": "2026"
    },
    {
      "id": "R-045",
      "name": "دلال الصبحي",
      "stars": 5,
      "tag": "الجدول",
      "text": "واجهة هادية ومريحة وما فيها زحمة.",
      "time_label": "2026"
    },
    {
      "id": "R-046",
      "name": "ثامر الرشيدي",
      "stars": 5,
      "tag": "الكويزات",
      "text": "الكويزات بعد ما أخلصها ترجعني لأخطائي وهذا اللي كنت أحتاجه.",
      "time_label": "2026"
    },
    {
      "id": "R-047",
      "name": "جمانة القصيمي",
      "stars": 5,
      "tag": "الكويزات",
      "text": "حلو إن فيه محاولة واحدة كل 24 ساعة… تجبرك تذاكر بدل تكرر اختبار.",
      "time_label": "2026"
    },
    {
      "id": "R-048",
      "name": "ريم المعيوف",
      "stars": 5,
      "tag": "سهولة الاستخدام",
      "text": "التحليل واضح، وعرفني أضعف قسمين عندي بدون لف ودوران.",
      "time_label": "2026"
    },
    {
      "id": "R-049",
      "name": "مها المعيوف",
      "stars": 5,
      "tag": "الجدول",
      "text": "الجدول اليومي خلاني ألتزم… أول مرة أحس إن عندي مسار.",
      "time_label": "2026"
    },
    {
      "id": "R-050",
      "name": "سهيل العقيل",
      "stars": 5,
      "tag": "الـPDF",
      "text": "البرنامج ساعدني أرتب وقتي حتى لو عندي 30 دقيقة بس.",
      "time_label": "2026"
    },
    {
      "id": "R-051",
      "name": "لمى الجهني",
      "stars": 5,
      "tag": "الـPDF",
      "text": "النتيجة مو بس رقم… عطاني خطة تناسب موعد اختباري.",
      "time_label": "2026"
    },
    {
      "id": "R-052",
      "name": "ربى العيد",
      "stars": 5,
      "tag": "الكويزات",
      "text": "أعجبني خيار إيقاف الشرح عشان أختبر نفسي بجد.",
      "time_label": "2026"
    },
    {
      "id": "R-053",
      "name": "ناصر الحريري",
      "stars": 5,
      "tag": "الخطة",
      "text": "الكويزات بعد ما أخلصها ترجعني لأخطائي وهذا اللي كنت أحتاجه.",
      "time_label": "2026"
    },
    {
      "id": "R-054",
      "name": "معاذ الشمري",
      "stars": 5,
      "tag": "الخطة",
      "text": "النتيجة مو بس رقم… عطاني خطة تناسب موعد اختباري.",
      "time_label": "2026"
    },
    {
      "id": "R-055",
      "name": "مرام الحارثي",
      "stars": 5,
      "tag": "التركيز",
      "text": "أعجبني خيار إيقاف الشرح عشان أختبر نفسي بجد.",
      "time_label": "2026"
    },
    {
      "id": "R-056",
      "name": "فاطمة البقمي",
      "stars": 5,
      "tag": "سهولة الاستخدام",
      "text": "البرنامج ساعدني أرتب وقتي حتى لو عندي 30 دقيقة بس.",
      "time_label": "2026"
    },
    {
      "id": "R-057",
      "name": "أسماء العسيري",
      "stars": 5,
      "tag": "التركيز",
      "text": "التحليل واضح، وعرفني أضعف قسمين عندي بدون لف ودوران.",
      "time_label": "2026"
    },
    {
      "id": "R-058",
      "name": "راشد الحازمي",
      "stars": 5,
      "tag": "الخطة",
      "text": "أعجبني خيار إيقاف الشرح عشان أختبر نفسي بجد.",
      "time_label": "2026"
    },
    {
      "id": "R-059",
      "name": "أحمد المهري",
      "stars": 5,
      "tag": "التركيز",
      "text": "أعجبني خيار إيقاف الشرح عشان أختبر نفسي بجد.",
      "time_label": "2026"
    },
    {
      "id": "R-060",
      "name": "لميس الطائي",
      "stars": 5,
      "tag": "الجدول",
      "text": "النتيجة مو بس رقم… عطاني خطة تناسب موعد اختباري.",
      "time_label": "2026"
    },
    {
      "id": "R-061",
      "name": "ليان السبيعي",
      "stars": 5,
      "tag": "الكويزات",
      "text": "البرنامج ساعدني أرتب وقتي حتى لو عندي 30 دقيقة بس.",
      "time_label": "2026"
    },
    {
      "id": "R-062",
      "name": "نورة الشراري",
      "stars": 5,
      "tag": "المساعد",
      "text": "ميزة تحميل الـPDF ممتازة — أحطه قدامي وأشيك الإنجاز.",
      "time_label": "2026"
    },
    {
      "id": "R-063",
      "name": "حسن العامري",
      "stars": 5,
      "tag": "منع التشتيت",
      "text": "التحليل واضح، وعرفني أضعف قسمين عندي بدون لف ودوران.",
      "time_label": "2026"
    },
    {
      "id": "R-064",
      "name": "العنود العامري",
      "stars": 5,
      "tag": "التركيز",
      "text": "أعجبني خيار إيقاف الشرح عشان أختبر نفسي بجد.",
      "time_label": "2026"
    },
    {
      "id": "R-065",
      "name": "سُرى السبيعي",
      "stars": 5,
      "tag": "التركيز",
      "text": "الجدول اليومي خلاني ألتزم… أول مرة أحس إن عندي مسار.",
      "time_label": "2026"
    },
    {
      "id": "R-066",
      "name": "مروان السلمي",
      "stars": 5,
      "tag": "المساعد",
      "text": "ميزة تحميل الـPDF ممتازة — أحطه قدامي وأشيك الإنجاز.",
      "time_label": "2026"
    },
    {
      "id": "R-067",
      "name": "آلاء السهلي",
      "stars": 5,
      "tag": "الجدول",
      "text": "البرنامج ساعدني أرتب وقتي حتى لو عندي 30 دقيقة بس.",
      "time_label": "2026"
    },
    {
      "id": "R-068",
      "name": "حسن العقيل",
      "stars": 5,
      "tag": "الـPDF",
      "text": "التحليل واضح، وعرفني أضعف قسمين عندي بدون لف ودوران.",
      "time_label": "2026"
    },
    {
      "id": "R-069",
      "name": "فارس الخثعمي",
      "stars": 5,
      "tag": "سهولة الاستخدام",
      "text": "النتيجة مو بس رقم… عطاني خطة تناسب موعد اختباري.",
      "time_label": "2026"
    },
    {
      "id": "R-070",
      "name": "مها السيف",
      "stars": 5,
      "tag": "المساعد",
      "text": "النتيجة مو بس رقم… عطاني خطة تناسب موعد اختباري.",
      "time_label": "2026"
    },
    {
      "id": "R-071",
      "name": "إبراهيم الطائي",
      "stars": 5,
      "tag": "الخطة",
      "text": "واجهة هادية ومريحة وما فيها زحمة.",
      "time_label": "2026"
    },
    {
      "id": "R-072",
      "name": "عبدالعزيز العتيبي",
      "stars": 5,
      "tag": "الجدول",
      "text": "النتيجة مو بس رقم… عطاني خطة تناسب موعد اختباري.",
      "time_label": "2026"
    },
    {
      "id": "R-073",
      "name": "سُهى العلوي",
      "stars": 5,
      "tag": "المساعد",
      "text": "أفضل شيء: ما تتشتت بين مصادر كثيرة.",
      "time_label": "2026"
    },
    {
      "id": "R-074",
      "name": "هيا الحمادي",
      "stars": 5,
      "tag": "الكويزات",
      "text": "التحليل واضح، وعرفني أضعف قسمين عندي بدون لف ودوران.",
      "time_label": "2026"
    },
    {
      "id": "R-075",
      "name": "رائد المهري",
      "stars": 5,
      "tag": "الكويزات",
      "text": "ميزة تحميل الـPDF ممتازة — أحطه قدامي وأشيك الإنجاز.",
      "time_label": "2026"
    },
    {
      "id": "R-076",
      "name": "مراد السهيمي",
      "stars": 5,
      "tag": "المساعد",
      "text": "واجهة هادية ومريحة وما فيها زحمة.",
      "time_label": "2026"
    },
    {
      "id": "R-077",
      "name": "طارق الطائي",
      "stars": 5,
      "tag": "منع التشتيت",
      "text": "أعجبني خيار إيقاف الشرح عشان أختبر نفسي بجد.",
      "time_label": "2026"
    },
    {
      "id": "R-078",
      "name": "عبدالله الدوخي",
      "stars": 5,
      "tag": "سهولة الاستخدام",
      "text": "أفضل شيء: ما تتشتت بين مصادر كثيرة.",
      "time_label": "2026"
    },
    {
      "id": "R-079",
      "name": "يقين الماجدي",
      "stars": 5,
      "tag": "المساعد",
      "text": "البرنامج ساعدني أرتب وقتي حتى لو عندي 30 دقيقة بس.",
      "time_label": "2026"
    },
    {
      "id": "R-080",
      "name": "سُديم العيد",
      "stars": 5,
      "tag": "سهولة الاستخدام",
      "text": "الجدول اليومي خلاني ألتزم… أول مرة أحس إن عندي مسار.",
      "time_label": "2026"
    },
    {
      "id": "R-081",
      "name": "ريان المري",
      "stars": 5,
      "tag": "الجدول",
      "text": "أعجبني خيار إيقاف الشرح عشان أختبر نفسي بجد.",
      "time_label": "2026"
    },
    {
      "id": "R-082",
      "name": "سُرى العتيبي",
      "stars": 5,
      "tag": "الخطة",
      "text": "حلو إن فيه محاولة واحدة كل 24 ساعة… تجبرك تذاكر بدل تكرر اختبار.",
      "time_label": "2026"
    },
    {
      "id": "R-083",
      "name": "منال الدوسري",
      "stars": 5,
      "tag": "الكويزات",
      "text": "أفضل شيء: ما تتشتت بين مصادر كثيرة.",
      "time_label": "2026"
    },
    {
      "id": "R-084",
      "name": "مازن المطرفي",
      "stars": 5,
      "tag": "الخطة",
      "text": "أعجبني خيار إيقاف الشرح عشان أختبر نفسي بجد.",
      "time_label": "2026"
    },
    {
      "id": "R-085",
      "name": "إلهام المري",
      "stars": 5,
      "tag": "سهولة الاستخدام",
      "text": "أفضل شيء: ما تتشتت بين مصادر كثيرة.",
      "time_label": "2026"
    },
    {
      "id": "R-086",
      "name": "أثير العقيل",
      "stars": 5,
      "tag": "الخطة",
      "text": "أفضل شيء: ما تتشتت بين مصادر كثيرة.",
      "time_label": "2026"
    },
    {
      "id": "R-087",
      "name": "روان الحميدي",
      "stars": 5,
      "tag": "التركيز",
      "text": "التحليل واضح، وعرفني أضعف قسمين عندي بدون لف ودوران.",
      "time_label": "2026"
    },
    {
      "id": "R-088",
      "name": "غيداء الكعبي",
      "stars": 5,
      "tag": "الكويزات",
      "text": "واجهة هادية ومريحة وما فيها زحمة.",
      "time_label": "2026"
    },
    {
      "id": "R-089",
      "name": "نجلاء الهاشمي",
      "stars": 5,
      "tag": "الـPDF",
      "text": "حلو إن فيه محاولة واحدة كل 24 ساعة… تجبرك تذاكر بدل تكرر اختبار.",
      "time_label": "2026"
    },
    {
      "id": "R-090",
      "name": "نورة الراشدي",
      "stars": 5,
      "tag": "الجدول",
      "text": "أفضل شيء: ما تتشتت بين مصادر كثيرة.",
      "time_label": "2026"
    },
    {
      "id": "R-091",
      "name": "مراد الحازمي",
      "stars": 5,
      "tag": "التركيز",
      "text": "التحليل واضح، وعرفني أضعف قسمين عندي بدون لف ودوران.",
      "time_label": "2026"
    },
    {
      "id": "R-092",
      "name": "دلال الزبيدي",
      "stars": 5,
      "tag": "الجدول",
      "text": "النتيجة مو بس رقم… عطاني خطة تناسب موعد اختباري.",
      "time_label": "2026"
    },
    {
      "id": "R-093",
      "name": "صالح الرشيدي",
      "stars": 5,
      "tag": "الجدول",
      "text": "حلو إن فيه محاولة واحدة كل 24 ساعة… تجبرك تذاكر بدل تكرر اختبار.",
      "time_label": "2026"
    },
    {
      "id": "R-094",
      "name": "حمد الرويلي",
      "stars": 5,
      "tag": "الجدول",
      "text": "الكويزات بعد ما أخلصها ترجعني لأخطائي وهذا اللي كنت أحتاجه.",
      "time_label": "2026"
    },
    {
      "id": "R-095",
      "name": "غلا الزيدي",
      "stars": 5,
      "tag": "المساعد",
      "text": "النتيجة مو بس رقم… عطاني خطة تناسب موعد اختباري.",
      "time_label": "2026"
    },
    {
      "id": "R-096",
      "name": "مهند الزيدي",
      "stars": 5,
      "tag": "الـPDF",
      "text": "أفضل شيء: ما تتشتت بين مصادر كثيرة.",
      "time_label": "2026"
    },
    {
      "id": "R-097",
      "name": "حنان العتيبي",
      "stars": 5,
      "tag": "المساعد",
      "text": "البرنامج ساعدني أرتب وقتي حتى لو عندي 30 دقيقة بس.",
      "time_label": "2026"
    },
    {
      "id": "R-098",
      "name": "مرام الهاجري",
      "stars": 5,
      "tag": "الخطة",
      "text": "البرنامج ساعدني أرتب وقتي حتى لو عندي 30 دقيقة بس.",
      "time_label": "2026"
    },
    {
      "id": "R-099",
      "name": "سُرى المطيري",
      "stars": 5,
      "tag": "سهولة الاستخدام",
      "text": "ميزة تحميل الـPDF ممتازة — أحطه قدامي وأشيك الإنجاز.",
      "time_label": "2026"
    },
    {
      "id": "R-100",
      "name": "سمر الشهري",
      "stars": 5,
      "tag": "الجدول",
      "text": "حلو إن فيه محاولة واحدة كل 24 ساعة… تجبرك تذاكر بدل تكرر اختبار.",
      "time_label": "2026"
    },
    {
      "id": "R-101",
      "name": "أسماء الهاشمي",
      "stars": 5,
      "tag": "الكويزات",
      "text": "الجدول اليومي خلاني ألتزم… أول مرة أحس إن عندي مسار.",
      "time_label": "2026"
    },
    {
      "id": "R-102",
      "name": "أثير المري",
      "stars": 5,
      "tag": "الكويزات",
      "text": "أعجبني خيار إيقاف الشرح عشان أختبر نفسي بجد.",
      "time_label": "2026"
    },
    {
      "id": "R-103",
      "name": "فيصل العسيري",
      "stars": 5,
      "tag": "الـPDF",
      "text": "حلو إن فيه محاولة واحدة كل 24 ساعة… تجبرك تذاكر بدل تكرر اختبار.",
      "time_label": "2026"
    },
    {
      "id": "R-104",
      "name": "أثير الشراري",
      "stars": 5,
      "tag": "الـPDF",
      "text": "أعجبني خيار إيقاف الشرح عشان أختبر نفسي بجد.",
      "time_label": "2026"
    },
    {
      "id": "R-105",
      "name": "ماجد الحجيلي",
      "stars": 5,
      "tag": "الخطة",
      "text": "ميزة تحميل الـPDF ممتازة — أحطه قدامي وأشيك الإنجاز.",
      "time_label": "2026"
    },
    {
      "id": "R-106",
      "name": "صالح القرني",
      "stars": 5,
      "tag": "الـPDF",
      "text": "الجدول اليومي خلاني ألتزم… أول مرة أحس إن عندي مسار.",
      "time_label": "2026"
    },
    {
      "id": "R-107",
      "name": "كوثر العقيل",
      "stars": 5,
      "tag": "المساعد",
      "text": "أفضل شيء: ما تتشتت بين مصادر كثيرة.",
      "time_label": "2026"
    },
    {
      "id": "R-108",
      "name": "إبراهيم الكعبي",
      "stars": 5,
      "tag": "الخطة",
      "text": "النتيجة مو بس رقم… عطاني خطة تناسب موعد اختباري.",
      "time_label": "2026"
    },
    {
      "id": "R-109",
      "name": "لُجين القرني",
      "stars": 5,
      "tag": "التركيز",
      "text": "حلو إن فيه محاولة واحدة كل 24 ساعة… تجبرك تذاكر بدل تكرر اختبار.",
      "time_label": "2026"
    },
    {
      "id": "R-110",
      "name": "رائد المطرفي",
      "stars": 5,
      "tag": "سهولة الاستخدام",
      "text": "النتيجة مو بس رقم… عطاني خطة تناسب موعد اختباري.",
      "time_label": "2026"
    },
    {
      "id": "R-111",
      "name": "يزيد الكيال",
      "stars": 5,
      "tag": "الخطة",
      "text": "ميزة تحميل الـPDF ممتازة — أحطه قدامي وأشيك الإنجاز.",
      "time_label": "2026"
    },
    {
      "id": "R-112",
      "name": "حنين الراشدي",
      "stars": 5,
      "tag": "الكويزات",
      "text": "الكويزات بعد ما أخلصها ترجعني لأخطائي وهذا اللي كنت أحتاجه.",
      "time_label": "2026"
    },
    {
      "id": "R-113",
      "name": "ليان الهاجري",
      "stars": 5,
      "tag": "منع التشتيت",
      "text": "النتيجة مو بس رقم… عطاني خطة تناسب موعد اختباري.",
      "time_label": "2026"
    },
    {
      "id": "R-114",
      "name": "لمى الحجيلي",
      "stars": 5,
      "tag": "الكويزات",
      "text": "النتيجة مو بس رقم… عطاني خطة تناسب موعد اختباري.",
      "time_label": "2026"
    },
    {
      "id": "R-115",
      "name": "ندى التميمي",
      "stars": 5,
      "tag": "سهولة الاستخدام",
      "text": "الكويزات بعد ما أخلصها ترجعني لأخطائي وهذا اللي كنت أحتاجه.",
      "time_label": "2026"
    },
    {
      "id": "R-116",
      "name": "هيا المنصوري",
      "stars": 5,
      "tag": "الجدول",
      "text": "التحليل واضح، وعرفني أضعف قسمين عندي بدون لف ودوران.",
      "time_label": "2026"
    },
    {
      "id": "R-117",
      "name": "عمر الصالحي",
      "stars": 5,
      "tag": "المساعد",
      "text": "حلو إن فيه محاولة واحدة كل 24 ساعة… تجبرك تذاكر بدل تكرر اختبار.",
      "time_label": "2026"
    },
    {
      "id": "R-118",
      "name": "سما العبدلي",
      "stars": 5,
      "tag": "التركيز",
      "text": "الكويزات بعد ما أخلصها ترجعني لأخطائي وهذا اللي كنت أحتاجه.",
      "time_label": "2026"
    },
    {
      "id": "R-119",
      "name": "سعود السلمي",
      "stars": 5,
      "tag": "منع التشتيت",
      "text": "الجدول اليومي خلاني ألتزم… أول مرة أحس إن عندي مسار.",
      "time_label": "2026"
    },
    {
      "id": "R-120",
      "name": "علي الحجيلي",
      "stars": 5,
      "tag": "التركيز",
      "text": "واجهة هادية ومريحة وما فيها زحمة.",
      "time_label": "2026"
    }
  ]
}